wagtail_table_block/__init__.py
wagtail_table_block/tests.py
wagtail_table_block/fields.py
wagtail_table_block/templates/table_block/blocks/table.html
wagtail_table_block/templates/table_block/widgets/table.html
wagtail_table_block/static/table_block/js/table.js
wagtail_table_block/static/table_block/js/vendor/handsontable-0.24.2.full.min.js
wagtail_table_block/static/table_block/css/vendor/handsontable-0.24.2.full.min.css
wagtail_table_block-2.0.0.dist-info/top_level.txt
wagtail_table_block-2.0.0.dist-info/DESCRIPTION.rst
wagtail_table_block-2.0.0.dist-info/METADATA
wagtail_table_block-2.0.0.dist-info/metadata.json
wagtail_table_block-2.0.0.dist-info/WHEEL
wagtail_table_block-2.0.0.dist-info/RECORD
