Metadata-Version: 2.0
Name: wagtail-table-block
Version: 2.0.0
Summary: Wagtail 1.5's table block in a separate package
Home-page: https://github.com/alexgleason/wagtail_table_block
Author: Alex Gleason
Author-email: alex@alexgleason.me
License: MIT
Keywords: development
Platform: UNKNOWN
Classifier: Environment :: Web Environment
Classifier: Framework :: Django
Classifier: Intended Audience :: Developers
Classifier: Operating System :: OS Independent
Classifier: Programming Language :: Python
Classifier: Topic :: Internet :: WWW/HTTP
Classifier: Topic :: Internet :: WWW/HTTP :: Dynamic Content
